jds_tools/hooks/__init__.py
jds_tools/hooks/base.py
jds_tools/hooks/google_hook.py
jds_tools/hooks/jinja_hook.py
jds_tools/hooks/snowflake_hook.py
jds_tools/utils/__init__.py
jds_tools/utils/async_requests.py
jds_tools/utils/path_utils.py
jds_tools-2.2.2.dist-info/LICENSE
jds_tools-2.2.2.dist-info/METADATA
jds_tools-2.2.2.dist-info/WHEEL
jds_tools-2.2.2.dist-info/top_level.txt
jds_tools-2.2.2.dist-info/RECORD
