Metadata-Version: 2.1
Name: jds-tools
Version: 2.2.2
Summary: Utility library designed for Data Science, Data Engineering, and Python Development projects
Home-page: https://github.com/juandaherrera/jds_tools
Author: Juan David Herrera
Author-email: juandaherreparra@gmail.com
License: MIT
Classifier: Programming Language :: Python :: 3
Classifier: License :: OSI Approved :: MIT License
Classifier: Operating System :: OS Independent
Requires-Python: >=3.10
License-File: LICENSE
Requires-Dist: snowflake-sqlalchemy ==1.5.3
Requires-Dist: pandas ==2.0.0
Requires-Dist: jinja2 <4.0.0,>=3.0.0
Requires-Dist: aiohttp ==3.9.5
Requires-Dist: gspread <7.0.0,>=6.0.0
